pdfmagic/main.py
pdfmagic-0.0.1.dist-info/LICENSE
pdfmagic-0.0.1.dist-info/METADATA
pdfmagic-0.0.1.dist-info/WHEEL
pdfmagic-0.0.1.dist-info/entry_points.txt
pdfmagic-0.0.1.dist-info/top_level.txt
pdfmagic-0.0.1.dist-info/RECORD
